gemaakmd_diffusion2d/__init__.py
gemaakmd_diffusion2d/diffusion2d.py
gemaakmd_diffusion2d/output.py
gemaakmd_diffusion2d-0.0.14.dist-info/LICENSE
gemaakmd_diffusion2d-0.0.14.dist-info/METADATA
gemaakmd_diffusion2d-0.0.14.dist-info/WHEEL
gemaakmd_diffusion2d-0.0.14.dist-info/top_level.txt
gemaakmd_diffusion2d-0.0.14.dist-info/RECORD
