Metadata-Version: 2.1
Name: gemaakmd_diffusion2d
Version: 0.0.14
Summary: SSE Python Exercise
Home-page: https://github.com/mgemaakbar/diffusion2D
Author: Muhammad Gema Akbar
License-File: LICENSE
Requires-Dist: matplotlib >=3.9.0
Requires-Dist: numpy >=2.1.0
